[
  {
    "status": "rejected",
    "reviewedAt": "2026-04-13T21:02:42.600Z",
    "reviewNote": "Test moderation",
    "id": "1776113841457",
    "submittedAt": "2026-04-13T20:57:21.457Z",
    "fullName": "Test Builder",
    "age": 21,
    "email": "test@example.com",
    "discord": "@builder",
    "timezone": "UTC+2",
    "experience": "Built lobby hubs and medieval towns for 3 years.",
    "portfolio": "https://example.com/portfolio",
    "availability": "12 hours",
    "motivation": "I want to join SyntrexStudio to create immersive maps and collaborate with a creative team."
  },
  {
    "status": "rejected",
    "reviewedAt": "2026-04-14T14:36:52.938Z",
    "reviewNote": "",
    "id": "1776123390687",
    "submittedAt": "2026-04-13T23:36:30.688Z",
    "fullName": "veljapriv",
    "age": 17,
    "email": "veljkom705@gmail.com",
    "discord": "test",
    "timezone": "utc",
    "experience": "http://localhost:3000http://localhost:3000http://localhost:3000http://localhost:3000http://localhost:3000http://localhost:3000",
    "portfolio": "https://panel.primesmp.fun/server/2bd4fa12",
    "availability": "sfafasfas",
    "motivation": "http://localhost:3000http://localhost:3000"
  },
  {
    "status": "pending",
    "reviewedAt": null,
    "reviewNote": "",
    "id": "1776177269967",
    "submittedAt": "2026-04-14T14:34:29.967Z",
    "fullName": "kurac na biciklu",
    "age": 67,
    "email": "awdadad@gmail.com",
    "discord": "kurcia#0000",
    "timezone": "UTC+1",
    "experience": "STFU NIGGE",
    "portfolio": "https://jovanstar.site",
    "availability": "AWDWA",
    "motivation": "DAWDAWadawddawdawdawdawdawdawd"
  },
  {
    "id": "1776269050389",
    "submittedAt": "2026-04-15T16:04:10.389Z",
    "fullName": "veljapriv",
    "age": 17,
    "email": "veljkom705@gmail.com",
    "discord": "test",
    "timezone": "utc",
    "experience": "sdasdasdsadasdadsdasdasdsadasdadsdasdasdsadasdadsdasdasdsadasdadsdasdasdsadasdadsdasdasdsadasdadsdasdasdsadasdadsdasdasdsadasdadsdasdasdsadasdad",
    "portfolio": "https://panel.primesmp.fun/server/2bd4fa12",
    "availability": "sfafasfas",
    "motivation": "sdasdasdsadasdadsdasdasdsadasdadsdasdasdsadasdad"
  }
]